{
  "auth": {
    "corre7fe20cbc": {
      "service": "Cognito",
      "serviceType": "imported",
      "providerPlugin": "awscloudformation",
      "dependsOn": [],
      "customAuth": false
    }
  },
  "geo": {
    "correMap": {
      "isDefault": true,
      "providerPlugin": "awscloudformation",
      "service": "Map",
      "mapStyle": "VectorEsriNavigation",
      "accessType": "AuthorizedAndGuestUsers",
      "dependsOn": [
        {
          "category": "auth",
          "resourceName": "corre7fe20cbc",
          "attributes": [
            "UserPoolId"
          ]
        }
      ]
    }
  }
}